LICENSE
MANIFEST.in
README.rst
setup.py
geokey_epicollect/__init__.py
geokey_epicollect/models.py
geokey_epicollect/serializer.py
geokey_epicollect/urls.py
geokey_epicollect/views.py
geokey_epicollect.egg-info/PKG-INFO
geokey_epicollect.egg-info/SOURCES.txt
geokey_epicollect.egg-info/dependency_links.txt
geokey_epicollect.egg-info/requires.txt
geokey_epicollect.egg-info/top_level.txt
geokey_epicollect/migrations/0001_initial.py
geokey_epicollect/migrations/0002_epicollectmedia.py
geokey_epicollect/migrations/__init__.py
geokey_epicollect/templates/epicollect_index.html