Metadata-Version: 1.1
Name: geokey-epicollect
Version: 1.0.3
Summary: Use EpiCollect to collect data for GeoKey
Home-page: https://github.com/ExCiteS/geokey-epicollect
Author: ExCiteS
Author-email: excites@ucl.ac.uk
License: MIT
Download-URL: https://github.com/ExCiteS/geokey-epicollect/tarball/1.0.3
Platform: UNKNOWN
